fridex/__init__.py
fridex-0.0.1.dist-info/LICENSE
fridex-0.0.1.dist-info/METADATA
fridex-0.0.1.dist-info/WHEEL
fridex-0.0.1.dist-info/top_level.txt
fridex-0.0.1.dist-info/RECORD
