Metadata-Version: 2.1
Name: fridex
Version: 0.0.1
Summary: Fridrich default package
Home-page: https://github.com/FridrichDerGosse/Fridrich
Author: Lukas Krahbichler
Author-email: melonenbuby@proton.me
Classifier: Programming Language :: Python :: 3.11
Classifier: License :: OSI Approved :: GNU General Public License v3 (GPLv3)
Classifier: Operating System :: OS Independent
Requires-Python: >=3.11
License-File: LICENSE
